{"scrapedAt":"2023-10-03 23:10:59","day":"Thursday,","date":"20 May 2021,","time":"03:00","homeTeam":"Everton","awayTeam":"Wolves","mlFirstHalf":[{"bookMakerName":"10x10bet","hw":"2.01","d":"2.42","aw":"4.33"},{"bookMakerName":"1xBet","hw":"2.22","d":"2.64","aw":"4.58"},{"bookMakerName":"bet-at-home","hw":"2.11","d":"2.55","aw":"4.30"},{"bookMakerName":"bet365","hw":"2.05","d":"2.50","aw":"4.50"},{"bookMakerName":"Interwetten","hw":"2.20","d":"2.40","aw":"4.60"},{"bookMakerName":"Lasbet","hw":"2.01","d":"2.42","aw":"4.33"},{"bookMakerName":"Marathonbet","hw":"2.14","d":"2.53","aw":"4.70"},{"bookMakerName":"Unibet","hw":"2.10","d":"2.50","aw":"4.50"},{"bookMakerName":"William Hill","hw":"2.15","d":"2.30","aw":"4.40"},{"bookMakerName":"Average","hw":"2.11","d":"2.47","aw":"4.47"},{"bookMakerName":"Highst","hw":"2.22","d":"2.64","aw":"4.70"},{"bookMakerName":"My coupon"}],"mlSecondHalf":[{"bookMakerName":"10x10bet","hw":"2.40","d":"2.21","aw":"5.10"},{"bookMakerName":"1xBet","hw":"2.41","d":"2.41","aw":"4.59"},{"bookMakerName":"bet-at-home","hw":"2.38","d":"2.12","aw":"4.80"},{"bookMakerName":"bet365","hw":"2.40","d":"2.25","aw":"4.75"},{"bookMakerName":"BetInAsia","hw":"2.61","d":"2.21","aw":"5.14"},{"bookMakerName":"GGBET","hw":"2.42","d":"2.14","aw":"5.14"},{"bookMakerName":"Interwetten","hw":"2.35","d":"2.15","aw":"4.90"},{"bookMakerName":"Lasbet","hw":"2.38","d":"2.22","aw":"5.20"},{"bookMakerName":"Marathonbet","hw":"2.34","d":"2.17","aw":"5.35"},{"bookMakerName":"Pinnacle","hw":"2.61","d":"2.22","aw":"5.16"},{"bookMakerName":"Unibet","hw":"2.35","d":"2.18","aw":"4.90"},{"bookMakerName":"William Hill","hw":"2.45","d":"1.95","aw":"5.00"},{"bookMakerName":"Average","hw":"2.42","d":"2.19","aw":"5.00"},{"bookMakerName":"Highst","hw":"2.61","d":"2.41","aw":"5.35"},{"bookMakerName":"My coupon"}],"mlFullTime":[{"bookMakerName":"10x10bet","hw":"1.77","d":"3.75","aw":"5.00"},{"bookMakerName":"1xBet","hw":"1.73","d":"4.13","aw":"4.76"},{"bookMakerName":"bet-at-home","hw":"1.81","d":"3.60","aw":"4.50"},{"bookMakerName":"bet365","hw":"1.72","d":"3.75","aw":"4.75"},{"bookMakerName":"BetInAsia","hw":"1.86","d":"3.57","aw":"4.88"},{"bookMakerName":"GGBET","hw":"1.79","d":"3.72","aw":"4.94"},{"bookMakerName":"Interwetten","hw":"1.80","d":"3.60","aw":"4.60"},{"bookMakerName":"Lasbet","hw":"1.79","d":"3.80","aw":"5.10"},{"bookMakerName":"Marathonbet","hw":"1.79","d":"3.74","aw":"5.05"},{"bookMakerName":"Pinnacle","hw":"1.85","d":"3.57","aw":"4.89"},{"bookMakerName":"Unibet","hw":"1.81","d":"3.70","aw":"4.90"},{"bookMakerName":"William Hill","hw":"1.75","d":"3.75","aw":"4.50"},{"bookMakerName":"Average","hw":"1.79","d":"3.72","aw":"4.82"},{"bookMakerName":"Highst","hw":"1.86","d":"4.13","aw":"5.10"},{"bookMakerName":"My coupon"}],"leagueName":"premier-league"}